bme280/__init__.py
bme280/const.py
bme280/reader.py
RPi.bme280-0.2.4.dist-info/LICENSE.rst
RPi.bme280-0.2.4.dist-info/METADATA
RPi.bme280-0.2.4.dist-info/WHEEL
RPi.bme280-0.2.4.dist-info/top_level.txt
RPi.bme280-0.2.4.dist-info/RECORD
