Metadata-Version: 2.1
Name: RPi.bme280
Version: 0.2.4
Summary: A library to drive a Bosch BME280 temperature, humidity, pressure sensor over I2C
Home-page: https://github.com/rm-hull/bme280
Author: Richard Hull
Author-email: richard.hull@destructuring-bind.org
License: MIT
Download-URL: https://github.com/rm-hull/bme280/tarball/0.2.4
Keywords: raspberry pi,orange pi,banana pi,rpi,bosch,BME280,i2c,temperature,humidity,pressure
Platform: UNKNOWN
Classifier: License :: OSI Approved :: MIT License
Classifier: Development Status :: 4 - Beta
Classifier: Intended Audience :: Education
Classifier: Intended Audience :: Developers
Classifier: Topic :: Education
Classifier: Topic :: System :: Hardware
Classifier: Programming Language :: Python :: 2
Classifier: Programming Language :: Python :: 2.7
Classifier: Programming Language :: Python :: 3
Classifier: Programming Language :: Python :: 3.4
Classifier: Programming Language :: Python :: 3.5
Classifier: Programming Language :: Python :: 3.6
Provides-Extra: qa
Provides-Extra: test
